setup.py
Salvia/Gnuplot.py
Salvia/Style.py
Salvia.egg-info/PKG-INFO
Salvia.egg-info/SOURCES.txt
Salvia.egg-info/dependency_links.txt
Salvia.egg-info/not-zip-safe
Salvia.egg-info/top_level.txt