Metadata-Version: 1.0
Name: Salvia
Version: 0.1
Summary: A gnuplot wrapper
Home-page: UNKNOWN
Author: Gregor Olenik
Author-email: itvgo@itv.uni-stuttgart.de
License: BSD
Platform: UNKNOWN
